Workbook

Sheet Start Here
A1: Vanguard Outreach System
A2: LinkedIn · Facebook · Cold email · Reddit (F5Bot) — the daily engine that feeds booked calls to the closer
A4: What this is | B4: Your daily outreach machine on top of the setters' cold calls. Every channel ends in the same place: a free demo for the business and a 15-minute walkthrough booked on Calendly.
A5: The funnel | B5: 1 Find (searches, groups, F5Bot alerts) → 2 Touch (connect, comment, email) → 3 Conversation (they reply) → 4 Demo (build it in 48h) → 5 Call booked → 6 Showed → 7 Won. Every lead lives in 'Lead Tracker' with a stage and a next-action date.
A6: Who to target where | B6: Facebook: local business owners in city and niche groups, plus 'can anyone recommend a web designer?' posts. LinkedIn: about half owners, half referral partners (bookkeepers, coaches, photographers, marketers who don't build sites); trades and salon owners are on LinkedIn less. Email: businesses with a weak website (they list an email). Reddit: people asking to hire someone to build a site.
A7: Daily loop | B7: Morning: read the automated digests (A1–A5), approve and send the drafted replies, then do the day's outreach to the targets in 'Daily KPIs'. End of day: fill in one row of 'Daily Log' and update 'Lead Tracker'. Friday: run the weekly review prompt (A6).
A8: What's automated | B8: Claude does the finding, reading, sorting and drafting every day (see 'Automations'). You approve and press send. Cold email sending runs on its own inside your email tool once the sequence is set up. Nothing gets posted or sent on LinkedIn, Facebook or Reddit without you: auto-sending there breaks their rules and gets accounts restricted.
A9: How to fill it in | B9: Yellow cells with blue text are yours to fill in or change. Black text is formulas or reference: leave it. Grey italic rows are worked examples showing the format.
A10: Tabs | B10: Daily KPIs · Daily Log · Funnel Math · Lead Tracker · Reply Playbook · Templates · Sequences · Daily Routine · Targets & Sources · Automations · Rules & Limits
A11: Before day 1 | B11: 1) Fill in your cities, niches and Calendly link in 'Targets & Sources'. 2) Join 10 Facebook groups and paste their links there. 3) Set up F5Bot alerts with the keywords listed. 4) Set up a separate cold-email domain and start its warm-up (2–3 weeks before full volume). 5) Paste prompts A2–A5 into Claude in Chrome and set them to repeat. 6) Tell Claude your time zone to schedule A1.
A13: Legend | B13: Input / yours to edit
B14: Example row (format only)

Sheet Daily KPIs
A1: Daily KPIs
A2: Weekday targets. Change the yellow numbers; everything else updates. Set 'Week starting' to this Monday to see progress.
A3: Week starting (Monday) | C3: 46314
A5: Log col | B5: Channel | C5: Activity | D5: Daily target | E5: Weekly target | F5: This week actual | G5: % of weekly target | H5: Why / how | I5: Safety cap
A6: B | B6: LinkedIn | C6: Connection requests sent | D6: 15 | E6: =D6*5 | F6: =SUMIFS('Daily Log'!B:B,'Daily Log'!$A:$A,">="&$C$3,'Daily Log'!$A:$A,"<"&$C$3+7) | G6: =IF(E6=0,"-",F6/E6) | H6: Owners + referral partners from prospect finder (A3). | I6: ~100 / week LinkedIn limit; stay ≤ 75
A7: C | B7: LinkedIn | C7: First messages to new connections | D7: 10 | E7: =D7*5 | F7: =SUMIFS('Daily Log'!C:C,'Daily Log'!$A:$A,">="&$C$3,'Daily Log'!$A:$A,"<"&$C$3+7) | G7: =IF(E7=0,"-",F7/E7) | H7: Template LI-02, personalised with one real detail. | I7: Only people who accepted
A8: D | B8: LinkedIn | C8: Comments on prospects' / community posts | D8: 5 | E8: =D8*5 | F8: =SUMIFS('Daily Log'!D:D,'Daily Log'!$A:$A,">="&$C$3,'Daily Log'!$A:$A,"<"&$C$3+7) | G8: =IF(E8=0,"-",F8/E8) | H8: Useful comments, not pitches. Puts your name in front of them before the DM.
A9: E | B9: Facebook | C9: Helpful comments in local groups | D9: 10 | E9: =D9*5 | F9: =SUMIFS('Daily Log'!E:E,'Daily Log'!$A:$A,">="&$C$3,'Daily Log'!$A:$A,"<"&$C$3+7) | G9: =IF(E9=0,"-",F9/E9) | H9: Value comments from A4 list. Builds recognition in the group. | I9: Follow each group's rules
A10: F | B10: Facebook | C10: Replies to 'need a website / recommend' posts | D10: 3 | E10: =D10*5 | F10: =SUMIFS('Daily Log'!F:F,'Daily Log'!$A:$A,">="&$C$3,'Daily Log'!$A:$A,"<"&$C$3+7) | G10: =IF(E10=0,"-",F10/E10) | H10: Every one found by A4, same day. Template FB-01 then FB-02. | I10: Do all you find
A11: G | B11: Facebook | C11: DMs to warm people (asked or engaged) | D11: 5 | E11: =D11*5 | F11: =SUMIFS('Daily Log'!G:G,'Daily Log'!$A:$A,">="&$C$3,'Daily Log'!$A:$A,"<"&$C$3+7) | G11: =IF(E11=0,"-",F11/E11) | H11: Only people who asked publicly or engaged with you. Template FB-02/FB-03. | I11: Never mass-DM group members
A12: H | B12: Email | C12: New cold emails sent | D12: 40 | E12: =D12*5 | F12: =SUMIFS('Daily Log'!H:H,'Daily Log'!$A:$A,">="&$C$3,'Daily Log'!$A:$A,"<"&$C$3+7) | G12: =IF(E12=0,"-",F12/E12) | H12: Weak-website businesses with a public email. Demo built before step 1. | I12: ≤ 25–30 per inbox per day after warm-up
A13: I | B13: Reddit | C13: Helpful replies to buying-intent posts | D13: 3 | E13: =D13*5 | F13: =SUMIFS('Daily Log'!I:I,'Daily Log'!$A:$A,">="&$C$3,'Daily Log'!$A:$A,"<"&$C$3+7) | G13: =IF(E13=0,"-",F13/E13) | H13: From the A1 digest, score 3+. Tips first, offer second. | I13: Follow subreddit rules
A14: J | B14: Network | C14: Referral-partner conversations started | D14: 2 | E14: =D14*5 | F14: =SUMIFS('Daily Log'!J:J,'Daily Log'!$A:$A,">="&$C$3,'Daily Log'!$A:$A,"<"&$C$3+7) | G14: =IF(E14=0,"-",F14/E14) | H14: Template LI-06, local events, chamber/BNI contacts.
A15: K | B15: Outcome | C15: New conversations (any channel) | D15: 8 | E15: =D15*5 | F15: =SUMIFS('Daily Log'!K:K,'Daily Log'!$A:$A,">="&$C$3,'Daily Log'!$A:$A,"<"&$C$3+7) | G15: =IF(E15=0,"-",F15/E15) | H15: Someone replied and a real back-and-forth started.
A16: L | B16: Outcome | C16: Demos built for warm leads | D16: 2 | E16: =D16*5 | F16: =SUMIFS('Daily Log'!L:L,'Daily Log'!$A:$A,">="&$C$3,'Daily Log'!$A:$A,"<"&$C$3+7) | G16: =IF(E16=0,"-",F16/E16) | H16: scripts/generate_demo.py; send within 48h of a yes. | I16: Never before they say yes, except email step 1
A17: M | B17: Outcome | C17: Calls booked | D17: 1 | E17: =D17*5 | F17: =SUMIFS('Daily Log'!M:M,'Daily Log'!$A:$A,">="&$C$3,'Daily Log'!$A:$A,"<"&$C$3+7) | G17: =IF(E17=0,"-",F17/E17) | H17: The number that matters. 5 a week feeds about 1–2 closes.
B19: Weekly-only targets
B20: LinkedIn | C20: Value posts on your profile (demo before/after, local business tips) | E20: 3
B21: Facebook | C21: Posts in groups that allow service offers (FB-04) | E21: 2
B22: Facebook | C22: New relevant groups joined | E22: 2
B23: Network | C23: Live or online networking event (chamber, BNI visit, Meetup) | E23: 1
B24: LinkedIn | C24: Withdraw invites pending 3+ weeks | E24: 1
B26: Targets are planning numbers chosen by Claude to fit platform limits and about 2 hours of outreach a day; adjust after two weeks of real data.

Sheet Daily Log
A1: Daily Log
A2: One row per weekday. Fill in the yellow cells at the end of each day (5 minutes). Score = average % of each activity target hit (capped at 100%).
A4: Date | B4: LI connects | C4: LI first msgs | D4: LI comments | E4: FB comments | F4: FB request replies | G4: FB warm DMs | H4: Emails sent | I4: Reddit replies | J4: Partner convos | K4: New convos | L4: Demos built | M4: Calls booked | N4: Total touches | O4: Activity score | P4: Notes
A5: Example | B5: 15 | C5: 10 | D5: 5 | E5: 8 | F5: 2 | G5: 4 | H5: 40 | I5: 3 | J5: 1 | K5: 6 | L5: 2 | M5: 1 | N5: =SUM(B5:J5) | O5: =IF(COUNT(B5:J5)=0,"",(MIN(B5/'Daily KPIs'!$D$6,1)+MIN(C5/'Daily KPIs'!$D$7,1)+MIN(D5/'Daily KPIs'!$D$8,1)+MIN(E5/'Daily KPIs'!$D$9,1)+MIN(F5/'Daily KPIs'!$D$10,1)+MIN(G5/'Daily KPIs'!$D$11,1)+MIN(H5/'Daily KPIs'!$D$12,1)+MIN(I5/'Daily KPIs'!$D$13,1)+MIN(J5/'Daily KPIs'!$D$14,1))/9) | P5: Example only — not counted in weekly totals
A6: 46314 | N6: =IF(COUNT(B6:J6)=0,"",SUM(B6:J6)) | O6: =IF(COUNT(B6:J6)=0,"",(MIN(B6/'Daily KPIs'!$D$6,1)+MIN(C6/'Daily KPIs'!$D$7,1)+MIN(D6/'Daily KPIs'!$D$8,1)+MIN(E6/'Daily KPIs'!$D$9,1)+MIN(F6/'Daily KPIs'!$D$10,1)+MIN(G6/'Daily KPIs'!$D$11,1)+MIN(H6/'Daily KPIs'!$D$12,1)+MIN(I6/'Daily KPIs'!$D$13,1)+MIN(J6/'Daily KPIs'!$D$14,1))/9)
A7: 46315 | N7: =IF(COUNT(B7:J7)=0,"",SUM(B7:J7)) | O7: =IF(COUNT(B7:J7)=0,"",(MIN(B7/'Daily KPIs'!$D$6,1)+MIN(C7/'Daily KPIs'!$D$7,1)+MIN(D7/'Daily KPIs'!$D$8,1)+MIN(E7/'Daily KPIs'!$D$9,1)+MIN(F7/'Daily KPIs'!$D$10,1)+MIN(G7/'Daily KPIs'!$D$11,1)+MIN(H7/'Daily KPIs'!$D$12,1)+MIN(I7/'Daily KPIs'!$D$13,1)+MIN(J7/'Daily KPIs'!$D$14,1))/9)
A8: 46316 | N8: =IF(COUNT(B8:J8)=0,"",SUM(B8:J8)) | O8: =IF(COUNT(B8:J8)=0,"",(MIN(B8/'Daily KPIs'!$D$6,1)+MIN(C8/'Daily KPIs'!$D$7,1)+MIN(D8/'Daily KPIs'!$D$8,1)+MIN(E8/'Daily KPIs'!$D$9,1)+MIN(F8/'Daily KPIs'!$D$10,1)+MIN(G8/'Daily KPIs'!$D$11,1)+MIN(H8/'Daily KPIs'!$D$12,1)+MIN(I8/'Daily KPIs'!$D$13,1)+MIN(J8/'Daily KPIs'!$D$14,1))/9)
A9: 46317 | N9: =IF(COUNT(B9:J9)=0,"",SUM(B9:J9)) | O9: =IF(COUNT(B9:J9)=0,"",(MIN(B9/'Daily KPIs'!$D$6,1)+MIN(C9/'Daily KPIs'!$D$7,1)+MIN(D9/'Daily KPIs'!$D$8,1)+MIN(E9/'Daily KPIs'!$D$9,1)+MIN(F9/'Daily KPIs'!$D$10,1)+MIN(G9/'Daily KPIs'!$D$11,1)+MIN(H9/'Daily KPIs'!$D$12,1)+MIN(I9/'Daily KPIs'!$D$13,1)+MIN(J9/'Daily KPIs'!$D$14,1))/9)
A10: 46318 | N10: =IF(COUNT(B10:J10)=0,"",SUM(B10:J10)) | O10: =IF(COUNT(B10:J10)=0,"",(MIN(B10/'Daily KPIs'!$D$6,1)+MIN(C10/'Daily KPIs'!$D$7,1)+MIN(D10/'Daily KPIs'!$D$8,1)+MIN(E10/'Daily KPIs'!$D$9,1)+MIN(F10/'Daily KPIs'!$D$10,1)+MIN(G10/'Daily KPIs'!$D$11,1)+MIN(H10/'Daily KPIs'!$D$12,1)+MIN(I10/'Daily KPIs'!$D$13,1)+MIN(J10/'Daily KPIs'!$D$14,1))/9)
A11: 46321 | N11: =IF(COUNT(B11:J11)=0,"",SUM(B11:J11)) | O11: =IF(COUNT(B11:J11)=0,"",(MIN(B11/'Daily KPIs'!$D$6,1)+MIN(C11/'Daily KPIs'!$D$7,1)+MIN(D11/'Daily KPIs'!$D$8,1)+MIN(E11/'Daily KPIs'!$D$9,1)+MIN(F11/'Daily KPIs'!$D$10,1)+MIN(G11/'Daily KPIs'!$D$11,1)+MIN(H11/'Daily KPIs'!$D$12,1)+MIN(I11/'Daily KPIs'!$D$13,1)+MIN(J11/'Daily KPIs'!$D$14,1))/9)
A12: 46322 | N12: =IF(COUNT(B12:J12)=0,"",SUM(B12:J12)) | O12: =IF(COUNT(B12:J12)=0,"",(MIN(B12/'Daily KPIs'!$D$6,1)+MIN(C12/'Daily KPIs'!$D$7,1)+MIN(D12/'Daily KPIs'!$D$8,1)+MIN(E12/'Daily KPIs'!$D$9,1)+MIN(F12/'Daily KPIs'!$D$10,1)+MIN(G12/'Daily KPIs'!$D$11,1)+MIN(H12/'Daily KPIs'!$D$12,1)+MIN(I12/'Daily KPIs'!$D$13,1)+MIN(J12/'Daily KPIs'!$D$14,1))/9)
A13: 46323 | N13: =IF(COUNT(B13:J13)=0,"",SUM(B13:J13)) | O13: =IF(COUNT(B13:J13)=0,"",(MIN(B13/'Daily KPIs'!$D$6,1)+MIN(C13/'Daily KPIs'!$D$7,1)+MIN(D13/'Daily KPIs'!$D$8,1)+MIN(E13/'Daily KPIs'!$D$9,1)+MIN(F13/'Daily KPIs'!$D$10,1)+MIN(G13/'Daily KPIs'!$D$11,1)+MIN(H13/'Daily KPIs'!$D$12,1)+MIN(I13/'Daily KPIs'!$D$13,1)+MIN(J13/'Daily KPIs'!$D$14,1))/9)
A14: 46324 | N14: =IF(COUNT(B14:J14)=0,"",SUM(B14:J14)) | O14: =IF(COUNT(B14:J14)=0,"",(MIN(B14/'Daily KPIs'!$D$6,1)+MIN(C14/'Daily KPIs'!$D$7,1)+MIN(D14/'Daily KPIs'!$D$8,1)+MIN(E14/'Daily KPIs'!$D$9,1)+MIN(F14/'Daily KPIs'!$D$10,1)+MIN(G14/'Daily KPIs'!$D$11,1)+MIN(H14/'Daily KPIs'!$D$12,1)+MIN(I14/'Daily KPIs'!$D$13,1)+MIN(J14/'Daily KPIs'!$D$14,1))/9)
A15: 46325 | N15: =IF(COUNT(B15:J15)=0,"",SUM(B15:J15)) | O15: =IF(COUNT(B15:J15)=0,"",(MIN(B15/'Daily KPIs'!$D$6,1)+MIN(C15/'Daily KPIs'!$D$7,1)+MIN(D15/'Daily KPIs'!$D$8,1)+MIN(E15/'Daily KPIs'!$D$9,1)+MIN(F15/'Daily KPIs'!$D$10,1)+MIN(G15/'Daily KPIs'!$D$11,1)+MIN(H15/'Daily KPIs'!$D$12,1)+MIN(I15/'Daily KPIs'!$D$13,1)+MIN(J15/'Daily KPIs'!$D$14,1))/9)
A16: 46328 | N16: =IF(COUNT(B16:J16)=0,"",SUM(B16:J16)) | O16: =IF(COUNT(B16:J16)=0,"",(MIN(B16/'Daily KPIs'!$D$6,1)+MIN(C16/'Daily KPIs'!$D$7,1)+MIN(D16/'Daily KPIs'!$D$8,1)+MIN(E16/'Daily KPIs'!$D$9,1)+MIN(F16/'Daily KPIs'!$D$10,1)+MIN(G16/'Daily KPIs'!$D$11,1)+MIN(H16/'Daily KPIs'!$D$12,1)+MIN(I16/'Daily KPIs'!$D$13,1)+MIN(J16/'Daily KPIs'!$D$14,1))/9)
A17: 46329 | N17: =IF(COUNT(B17:J17)=0,"",SUM(B17:J17)) | O17: =IF(COUNT(B17:J17)=0,"",(MIN(B17/'Daily KPIs'!$D$6,1)+MIN(C17/'Daily KPIs'!$D$7,1)+MIN(D17/'Daily KPIs'!$D$8,1)+MIN(E17/'Daily KPIs'!$D$9,1)+MIN(F17/'Daily KPIs'!$D$10,1)+MIN(G17/'Daily KPIs'!$D$11,1)+MIN(H17/'Daily KPIs'!$D$12,1)+MIN(I17/'Daily KPIs'!$D$13,1)+MIN(J17/'Daily KPIs'!$D$14,1))/9)
... A45: 46367 | N45: =IF(COUNT(B45:J45)=0,"",SUM(B45:J45)) | O45: =IF(COUNT(B45:J45)=0,"",(MIN(B45/'Daily KPIs'!$D$6,1)+MIN(C45/'Daily KPIs'!$D$7,1)+MIN(D45/'Daily KPIs'!$D$8,1)+MIN(E45/'Daily KPIs'!$D$9,1)+MIN(F45/'Daily KPIs'!$D$10,1)+MIN(G45/'Daily KPIs'!$D$11,1)+MIN(H45/'Daily KPIs'!$D$12,1)+MIN(I45/'Daily KPIs'!$D$13,1)+MIN(J45/'Daily KPIs'!$D$14,1))/9)
A47: Totals | B47: =SUM(B6:B45) | C47: =SUM(C6:C45) | D47: =SUM(D6:D45) | E47: =SUM(E6:E45) | F47: =SUM(F6:F45) | G47: =SUM(G6:G45) | H47: =SUM(H6:H45) | I47: =SUM(I6:I45) | ... N47: =SUM(N6:N45)
A48: Avg score | O48: =IFERROR(AVERAGE(O6:O45),"-")
A49: Add more dated rows above the Totals row when you run out; copy the formulas in N and O down.

Sheet Funnel Math
A1: Funnel Math
A2: What the daily KPIs should produce. Yellow = planning assumptions: replace with your real rates after two weeks.
A4: Line | B4: LinkedIn | C4: Facebook | D4: Email | E4: Reddit | F4: Total | G4: Note
A5: Daily touches (from Daily KPIs) | B5: ='Daily KPIs'!D6 | C5: ='Daily KPIs'!D9+'Daily KPIs'!D10+'Daily KPIs'!D11 | D5: ='Daily KPIs'!D12 | E5: ='Daily KPIs'!D13 | F5: =SUM(B5:E5) | G5: LinkedIn counts connection requests; Facebook counts comments + request replies + warm DMs.
A6: Working days per month | B6: 22 | C6: 22 | D6: 22 | E6: 22 | G6: Weekdays only.
A7: Monthly touches | B7: =B5*B6 | C7: =C5*C6 | D7: =D5*D6 | E7: =E5*E6 | F7: =SUM(B7:E7)
A8: Conversation rate (touch → real conversation) | B8: 0.06 | C8: 0.08 | D8: 0.015 | E8: 0.2 | G8: Planning assumptions, not measured. LinkedIn ≈ 30% accept × 20% reply. Email ≈ 3% reply × 50% positive. Facebook mixes comments (low) and replies to people asking (high). Reddit counts only buying-intent posts.
A9: Conversations per month | B9: =B7*B8 | C9: =C7*C8 | D9: =D7*D8 | E9: =E7*E8 | F9: =SUM(B9:E9)
A10: Booked rate (conversation → call booked) | B10: 0.25 | C10: 0.2 | D10: 0.5 | E10: 0.25 | G10: Planning assumptions. Email replies already saw the demo, so they book more often.
A11: Calls booked per month | B11: =B9*B10 | C11: =C9*C10 | D11: =D9*D10 | E11: =E9*E10 | F11: =SUM(B11:E11)
A13: From booked call to revenue
A14: Show rate | B14: 0.7 | G14: Planning assumption (same as PIPELINE.md).
A15: Close rate (of calls that show) | B15: 0.3 | G15: Planning assumption (same as PIPELINE.md).
A16: Average project ($) | B16: 997 | G16: Foundation price; raise toward $1,497 as more clients take Full Presence.
A17: Calls held per month | B17: =F11*B14
A18: Closes per month | B18: =B17*B15
A19: Project revenue per month ($) | B19: =B18*B16 | G19: One-time build fees only; Care Plan not included.
A20: Your build capacity per month | B20: 6 | G20: From your delivery plan: about 5–6 builds a month.
A21: Capacity check | B21: =IF(B18>B20,"Over capacity — hire help or slow outreach","Within capacity")

Sheet Lead Tracker
A1: Lead Tracker
A2: Every person you're talking to, one row each. Sort or filter by 'Next action date'. Red = follow-up overdue.
A4: Date added | B4: Name | C4: Business | D4: Niche | E4: City, State | F4: Channel | G4: Source (link / group / post) | H4: Stage | I4: Reply type | J4: Last touch | K4: Touch # | L4: Next action | M4: Next action date | N4: Demo link | O4: Notes | P4: Days since touch | Q4: Overdue?
A5: 46314 | B5: Maria Lopez | C5: Glow Studio Nails | D5: Beauty | E5: Tampa, FL | F5: Facebook | G5: Tampa Small Business Owners group — 'anyone know a web designer?' | H5: Demo sent | I5: Wants demo | J5: 46315 | K5: 2 | L5: Book walkthrough | M5: 46317 | N5: https://demo.example/glow-studio | O5: Wants online booking; mostly Instagram today | P5: =IF(J5="","",TODAY()-J5) | Q5: =IF(AND(M5<>"",M5<TODAY(),ISNA(MATCH(H5,{"Won","Lost","Do not contact"},0))),"OVERDUE","")
P6: =IF(J6="","",TODAY()-J6) | Q6: =IF(AND(M6<>"",M6<TODAY(),ISNA(MATCH(H6,{"Won","Lost","Do not contact"},0))),"OVERDUE","")
P7: =IF(J7="","",TODAY()-J7) | Q7: =IF(AND(M7<>"",M7<TODAY(),ISNA(MATCH(H7,{"Won","Lost","Do not contact"},0))),"OVERDUE","")
P8: =IF(J8="","",TODAY()-J8) | Q8: =IF(AND(M8<>"",M8<TODAY(),ISNA(MATCH(H8,{"Won","Lost","Do not contact"},0))),"OVERDUE","")
P9: =IF(J9="","",TODAY()-J9) | Q9: =IF(AND(M9<>"",M9<TODAY(),ISNA(MATCH(H9,{"Won","Lost","Do not contact"},0))),"OVERDUE","")
P10: =IF(J10="","",TODAY()-J10) | Q10: =IF(AND(M10<>"",M10<TODAY(),ISNA(MATCH(H10,{"Won","Lost","Do not contact"},0))),"OVERDUE","")
P11: =IF(J11="","",TODAY()-J11) | Q11: =IF(AND(M11<>"",M11<TODAY(),ISNA(MATCH(H11,{"Won","Lost","Do not contact"},0))),"OVERDUE","")
P12: =IF(J12="","",TODAY()-J12) | Q12: =IF(AND(M12<>"",M12<TODAY(),ISNA(MATCH(H12,{"Won","Lost","Do not contact"},0))),"OVERDUE","")
P13: =IF(J13="","",TODAY()-J13) | Q13: =IF(AND(M13<>"",M13<TODAY(),ISNA(MATCH(H13,{"Won","Lost","Do not contact"},0))),"OVERDUE","")
P14: =IF(J14="","",TODAY()-J14) | Q14: =IF(AND(M14<>"",M14<TODAY(),ISNA(MATCH(H14,{"Won","Lost","Do not contact"},0))),"OVERDUE","")
P15: =IF(J15="","",TODAY()-J15) | Q15: =IF(AND(M15<>"",M15<TODAY(),ISNA(MATCH(H15,{"Won","Lost","Do not contact"},0))),"OVERDUE","")
P16: =IF(J16="","",TODAY()-J16) | Q16: =IF(AND(M16<>"",M16<TODAY(),ISNA(MATCH(H16,{"Won","Lost","Do not contact"},0))),"OVERDUE","")
P17: =IF(J17="","",TODAY()-J17) | Q17: =IF(AND(M17<>"",M17<TODAY(),ISNA(MATCH(H17,{"Won","Lost","Do not contact"},0))),"OVERDUE","")
... P505: =IF(J505="","",TODAY()-J505) | Q505: =IF(AND(M505<>"",M505<TODAY(),ISNA(MATCH(H505,{"Won","Lost","Do not contact"},0))),"OVERDUE","")

Sheet Reply Playbook
A1: Reply Playbook
A2: When someone replies on any channel: find the type, do what it says, move the stage. Answer every reply within 2 business hours.
A4: Reply type | B4: Sounds like | C4: What to do | D4: Template | E4: Move stage to | F4: Follow up if no answer
A5: Interested | B5: "Tell me more", "how does it work?" | C5: Answer in 2 lines, ask one question about their business, offer the free demo. | D5: RP-01 | E5: Conversation | F5: 24 hours
A6: Price question | B6: "How much?", "what does it cost?" | C6: Honest ballpark: most builds land around $1,000, one-time; the demo is free. Then offer the demo. Never quote exact prices, discounts or payment plans in DMs. | D6: RP-02 | E6: Conversation | F6: 48 hours
A7: Send info | B7: "Send me examples", "do you have a website?" | C7: Two portfolio links plus the offer to build their own demo. | D7: RP-03 | E7: Conversation | F7: 48 hours
A8: Wants demo | B8: "Sure, go ahead", "yes please" | C8: Get business name + any page (Google/Facebook/Instagram). Build within 48h with generate_demo.py. Send the demo with the Calendly link. | D8: RP-04 | E8: Demo building → Demo sent | F8: Day 2 and day 5 after sending
A9: Not now | B9: "Busy season", "maybe next month" | C9: Ask when to check back. Set the next action date to that day. | D9: RP-05 | E9: Nurture | F9: On the date they gave
A10: Has a website | B10: "Already have one", "my nephew did it" | C10: Respect it. Offer a free 3-point review of the current site. No pressure. | D10: RP-06 | E10: Nurture | F10: 30 days
A11: Referral | B11: "Talk to my friend", "you should contact X" | C11: Thank them, ask for an intro or permission to mention them. Add the new lead with Channel = Referral. | D11: RP-07 | E11: (new lead) Contacted | F11: 48 hours
A12: Partner | B12: A bookkeeper/coach/marketer who works with owners | C12: Book a 20-min partner call. Agree how you'll pass clients both ways. | D12: RP-08 | E12: Conversation | F12: 48 hours
A13: Not interested | B13: "No thanks", "not for us" | C13: One polite line. No further outreach. | D13: RP-09 | E13: Lost | F13: None
A14: Opt-out | B14: "Stop", "remove me", "unsubscribe", anger | C14: No sales reply. Add to Do-Not-Contact everywhere today (email suppression list too). | D14: — | E14: Do not contact | F14: Never
A15: Auto-reply | B15: Out of office, vacation | C15: Set next action date to their return date + 1 day. | D15: — | E15: (unchanged) | F15: Return date + 1
... A18: Booked | B18: They picked a time | C18: Confirm, send the demo link before the call, add to GHL with source tag, Slack posts automatically. | D18: RP-12 | E18: Call booked | F18: Reminders run in GHL/Calendly

Sheet Templates
A1: Templates
A2: Starting points. Always personalise with one real detail. Replace [brackets]. Never claim a demo exists until it does.
A4: ID | B4: Channel | C4: When | D4: Message
A5: LI-01 | B5: LinkedIn | C5: Connection request | D5: Send without a note (free accounts get only a few personalised notes a month). If you have notes: "Hi [First name], I build websites for local [niche] businesses around [city]. Would be good to connect."
A6: LI-02 | B6: LinkedIn | C6: Day 0 after they accept | D6: Thanks for connecting, [First name]. Quick one: I noticed [Business] [doesn't have a website yet / isn't easy to book from on a phone]. I build sites for local businesses and usually make a free demo first so owners can see it before deciding anything. Want me to put one together for you?
A7: LI-03 | B7: LinkedIn | C7: Day 3, no reply | D7: Hi [First name], no worries if now's not the time. Happy to make the free demo whenever suits. Should I go ahead?
A8: LI-04 | B8: LinkedIn | C8: Day 7, last touch | D8: Last note from me, [First name]. If a website's ever on the list for [Business], I'm here. All the best either way.
A9: LI-05 | B9: LinkedIn | C9: Comment on a 'need a website' post | D9: Happy to help here. I build sites for local businesses, live within 14 days of kick-off. I can mock up a free demo so you can see it before deciding. Sending you a message.
A10: LI-06 | B10: LinkedIn | C10: Referral partner opener | D10: Hi [First name], I see you work with [small business owners / salons / contractors] in [city]. A lot of them don't have a proper website, which is what I build. Open to passing clients both ways where it fits? Happy to grab 15 minutes.
A11: FB-01 | B11: Facebook | C11: Comment on a recommendation request | D11: Hi [Name]! I build websites for local businesses (Vanguard). Happy to make you a free demo so you can see it before deciding anything. I'll send you a message.
A12: FB-02 | B12: Facebook | C12: DM after their request | D12: Hi [Name], saw your post in [Group] about a website for [Business]. I'm [Your name] from Vanguard; we build sites for local [niche] businesses, live within 14 days of kick-off. If you send me your business name or page, I'll put together a free demo so you can see it first. Want me to?
A13: FB-03 | B13: Facebook | C13: DM to someone who engaged with you | D13: Thanks for [commenting on / liking] my post, [Name]! Is a website something you've been thinking about for [Business]? Happy to mock up a free demo if it's useful.
A14: FB-04 | B14: Facebook | C14: Group post (only where offers are allowed) | D14: For [City] business owners: this week I'm building [3] free demo websites, using your real services and photos. No strings: if you like it we can talk about making it live, if not you've lost nothing. Comment 'demo' or message me. [Only post a number you'll stick to.]
A15: EM-01 | B15: Email | C15: Step 1 (demo already built) | D15: Subject: [Business] website idea Hi [First name], I was looking at [Business] on Google ([rating] stars from [count] reviews, nice work). I noticed [the site is hard to use on a phone / there's no online booking]. We built a free demo of what an updated site could look like: [demo link]. If you'd like a 15-minute walkthrough, grab a time here: [Calendly link]. [Your name] · Vanguard · [physical mailing address] Reply "no thanks" and I won't email again.
... A31: RP-12 | B31: Any | C31: Booked | D31: You're booked, you'll get a confirmation from Calendly. I'll send the demo link before the call. Looking forward to it!

Sheet Sequences
A1: Sequences
A2: The cadence for each channel. Stop the sequence the moment they reply; switch to the Reply Playbook.
A4: Channel | B4: Day 0 | C4: Day 2–3 | D4: Day 5–7 | E4: Day 10–14 | F4: Then
A5: LinkedIn | B5: Connection request (LI-01) + like/comment on a recent post | C5: If accepted: LI-02 | D5: LI-03 | E5: LI-04 (last) | F5: Nurture: comment on their posts monthly
A6: Facebook | B6: Comment (FB-01) on their request, or a value comment | C6: DM (FB-02/FB-03) if they asked or engaged | D6: One follow-up DM if they read it | E6: Stop | F6: Stay visible in the group
A7: Email | B7: EM-01 (demo already built) | C7: EM-02 (day 3) | D7: EM-03 (day 7) | E7: EM-04 (day 12) | F7: Remove from sequence; nurture after 90 days only if no opt-out
A8: Reddit | B8: Public reply (RD-01) | C8: Answer follow-up questions in thread | D8: DM only if they ask you to | E8: Stop | F8: —
A9: Partner | B9: LI-06 or intro at an event | C9: Partner call | D9: Send 1-page referral info | E9: Check in monthly | F9: Pass them a referral when you can

Sheet Daily Routine
A1: Daily Routine
A2: About 2.5 hours of outreach a day, around your closing calls and builds. Times are your local time; change them to suit.
A4: Time | B4: Block | C4: What you do | D4: Minutes | E4: Feeds KPI
A5: 8:00 | B5: Read the digests | C5: Read the A1 (Reddit) and A2/A5 (LinkedIn, email) outputs. Approve and send the drafted replies; post Reddit replies yourself. | D5: 20 | E5: New convos, Reddit replies
A6: 8:20 | B6: Warm conversations first | C6: Answer every reply on every channel using the Reply Playbook. Update Lead Tracker stages. | D6: 20 | E6: New convos, Calls booked
A7: 8:40 | B7: LinkedIn | C7: Send 15 connection requests and 10 first messages from the A3 list; leave 5 useful comments. | D7: 40 | E7: LI connects, msgs, comments
A8: 9:20 | B8: Facebook | C8: Work the A4 output: reply to every website request, 10 value comments, warm DMs. | D8: 40 | E8: FB comments, replies, DMs
A9: 10:00 | B9: Partners | C9: 2 referral-partner conversations (LinkedIn, email or a call). | D9: 15 | E9: Partner convos
A10: 10:15 | B10: Build demos | C10: Build demos for everyone who said yes (aim for 2). Send each with the Calendly link. | D10: 60 | E10: Demos built
A11: Afternoon | B11: Closing calls and delivery | C11: Your closer calls and client builds. | D11: — | E11: —
A12: 16:30 | B12: Second sweep | C12: Read the afternoon A2/A5 outputs, answer new replies. | D12: 15 | E12: New convos
A13: 16:45 | B13: Log the day | C13: Fill in today's row in Daily Log; set next action dates in Lead Tracker. | D13: 10 | E13: All
A14: Mon | B14: Weekly setup | C14: Join 2 new groups, set the week in Daily KPIs, plan 3 LinkedIn posts. | D14: 30 | E14: Weekly targets
A15: Tue / Thu | B15: Post | C15: LinkedIn value post (demo before/after, a local business tip). Group post where allowed. | D15: 20 | E15: Weekly targets
A16: Wed | B16: Network | C16: One networking event (chamber, BNI visit, Meetup), in person or online. | D16: 60 | E16: Partner convos
A17: Fri | B17: Weekly review | C17: Run prompt A6 with this workbook attached. Change one thing for next week. | D17: 20 | E17: —

Sheet Targets & Sources
A1: Targets & Sources
A2: Where to find people. Fill in the yellow cells once; the prompts reference them.
A4: Channel | B4: What | C4: Use this | D4: Your value
A5: All | B5: Target cities | C5: Start with 3–5 US metros where you already have clients or demos. Use the same cities in every channel. | D5: [e.g. Tampa FL, Dallas TX, Columbus OH]
A6: All | B6: Target niches | C6: Beauty & wellness, fitness, trades, auto, pet & local services (your industry playbooks). | D6: [your top 3]
A7: All | B7: Calendly link | C7: Used in every template. | D7: [paste link]
A8: All | B8: Portfolio links | C8: Two best live sites (e.g. Elixa Beauty, MagniFit) for 'send info' replies. | D8: [paste 2 links]
A9: LinkedIn | B9: People search: owners | C9: Titles: Owner, Founder, Co-owner · Company size 1–10 · Locations: your cities · Industries: personal care, wellness & fitness, construction, automotive, restaurants, retail, pet services.
A10: LinkedIn | B10: People search: referral partners | C10: Bookkeepers, accountants, business coaches, photographers, print/sign shops, insurance agents, marketing freelancers who don't build sites — in your cities.
A11: LinkedIn | B11: Post search (buying signals) | C11: Posts, past 24 hours: "need a website", "looking for a web designer", "recommend a web designer", "website for my business", "anyone know a web developer".
A12: LinkedIn | B12: Communities | C12: Local chamber of commerce pages and events, city small-business groups, BNI chapters in your cities. | D12: [list the ones you join]
A13: Facebook | B13: Groups to find | C13: Search: "[City] small business", "[City] business owners", "[City] entrepreneurs", "[City] moms" (lots of recommendation requests), "salon owners", "barbershop owners", "contractors business", "[niche] business owners USA".
A14: Facebook | B14: Your groups (links) | C14: Paste the 10–20 groups you joined. Note which allow service posts. | D14: [paste group links]
A15: Facebook | B15: Keywords inside groups | C15: website · web designer · web developer · recommend · anyone know · need a site · Wix · Squarespace
A16: Reddit | B16: F5Bot keywords (f5bot.com, free) | C16: "need a website" · "looking for a web designer" · "recommend a web designer" · "website for my business" · "build me a website" · "hire a web designer" · "small business website" | D16: [alerts go to scarwhitthread@outlook.com]
A17: Reddit | B17: Subreddits to watch | C17: r/smallbusiness · r/Entrepreneur · r/forhire · r/hiring · r/sweatystartup · r/web_design · your target cities' subreddits. Read each one's self-promotion rules.
A18: Email | B18: Who to email | C18: Businesses whose website is weak (slow, no mobile layout, no booking) and that list an email on the site or Google profile. Businesses with no website rarely list an email; they go to the setters' call list instead.
A19: Email | B19: Sending setup | C19: A separate domain (e.g. getvanguard[.]co) with 2 inboxes, SPF/DKIM/DMARC set, 2–3 weeks warm-up. Send from GHL with a dedicated sending domain, or a cold-email tool such as Instantly or Smartlead. | D19: [your sending domain]
A20: Network | B20: In person / online | C20: Chamber of commerce mixers, BNI visitor days, Meetup small-business events, SCORE workshops in your cities.

Sheet Automations
A1: Automations
A2: The daily jobs. Claude finds, reads, sorts and drafts; you approve and send. Full prompt text is in column F (also in agency/OUTREACH_PROMPTS.md).
A4: ID | B4: Job | C4: When | D4: Where it runs | E4: Status | F4: Prompt (copy all of it)
A5: A1 | B5: Reddit leads digest (F5Bot → Outlook) | C5: Daily, 7:45am | D5: Claude Code scheduled task (cloud) with the Outlook (Mailbox) connector | E5: Ready to schedule — needs your time zone | F5: You are my lead scout for Vanguard, a web studio that builds websites for US local businesses (about $1,000 one-time, live within 14 days of kick-off, free demo first). 1. Using the Outlook (Mailbox) connector, make ONE search_emails call: from "f5bot", since yesterday's date, limit 25. The mailbox is on a free plan of 5 calls per day, so use at most 3 more calls in total (read_email only when a preview has no post link). Never send, move or delete email. 2. From the alerts, collect every Reddit post or comment URL. 3. For each URL, fetch the post (try the URL with ".json" on the end, or old.reddit.com). Skip anything older than 72 hours, locked, or already answered by a hired designer. 4. Score each one 1–5 for buying intent: 5 = a business owner asking to hire someone to build a website now; 3 = asking for recommendations or prices; 1 = a developer, student, job seeker or general discussion. 5. For every post scoring 3+, draft a reply that leads with 2–3 genuinely useful tips for their situation, then one line: "If you want it done for you, I run a small web studio (Vanguard) and can mock up a free demo so you can judge it first." Check the subreddit's rules in the sidebar: if self-promotion is banned, draft a tips-only reply and say so. 6. Output a digest table, best first: score, subreddit, post title, link, age, what they need (one line), drafted reply. End with: "Post replies yourself after checking each thread." Do not post anything to Reddit.
A6: A2 | B6: LinkedIn inbox triage | C6: Daily, 8:15am and 4:30pm | D6: Claude in Chrome on your computer (logged into LinkedIn) | E6: Paste into Claude in Chrome and set to repeat daily | F6: Open https://www.linkedin.com/messaging/ in a new tab. I run Vanguard, a web studio that builds websites for US local businesses (about $1,000 one-time, live within 14 days of kick-off, free demo first). 1. Open every conversation that is unread, or where the other person wrote last in the past 7 days. 2. For each one, classify the reply: Reply types (pick one per conversation): Interested · Price question · Send info · Wants demo · Not now · Has a website · Referral · Partner · Not interested · Opt-out · Auto-reply · Wrong person · Booked · Who are you 3. Draft my reply using the matching template from the Reply Playbook below, personalised with one detail from their message or profile. Keep it under 80 words, warm, no hard sell. If they want a demo, ask for their business name and any Google/Facebook/Instagram page. 4. Also check My Network → Invitations (list them, do not accept or decline) and Notifications for comments on my posts that need an answer. 5. Output a table: name, company, reply type, their last message (one line), my drafted reply, next stage, follow-up date. Reply Playbook: - Price question → "Fair question. It depends on what you need, but most of our builds land around $1,000, one-time, and the demo is free. Want me to put one together so you can see what you'd get?" - Send info → share two portfolio links and offer a free demo for their business. - Wants demo → ask for business name + any page; promise the demo within 48 hours, then book a 15-min walkthrough: [Calendly link]. - Not now → ask when to check back; set the follow-up date. - Has a website → offer a free 3-point review, no pressure. - Referral → thank them and ask for an intro. - Not interested / Opt-out → one polite line, then mark Do-Not-Contact. Rules: never send, post, comment, connect, accept or decline anything without my approval in this chat. Never invent facts about a prospect or about Vanguard. Prices: only the ballpark "most of our builds land around $1,000, one-time; the demo is free". Anyone who says stop / not interested / remove me goes on the Do-Not-Contact list and gets no further outreach.
A7: A3 | B7: LinkedIn prospect finder | C7: Weekdays, 9:15am | D7: Claude in Chrome on your computer | E7: Paste into Claude in Chrome and set to repeat on weekdays | F7: Find today's LinkedIn prospects for Vanguard (websites for US local businesses). Do not send any connection requests or messages. Part A — buying signals (do first): Search LinkedIn posts from the past 24 hours (Posts filter, sort by latest) for each of: "need a website", "looking for a web designer", "recommend a web designer", "website for my business", "anyone know a web developer". List posts by business owners or people asking on behalf of one. For each: author, link, what they need, and a drafted comment (helpful, mentions I can mock up a free demo) plus a drafted DM. Part B — owners and referral partners (up to 15 people in total): Search People with: titles Owner / Founder / Co-owner; company size 1–10; locations from my target list [CITIES]; industries: personal care, wellness and fitness, construction, automotive, restaurants, retail, pet services. Also find up to 5 referral partners in the same cities: bookkeepers, accountants, business coaches, photographers, print/sign shops, marketing freelancers who don't build websites. Skip anyone I'm already connected with or have a pending invite to. For each person: name, title, business, city, profile link, whether their business has a website (check the company page or a quick Google search), and one personalised first message to send after they accept (under 60 words, mentions one real detail, offers a free demo for owners or a referral swap for partners). Output: two tables (A and B), ready for me to action. Rules: never send, post, comment, connect, accept or decline anything without my approval in this chat. Never invent facts about a prospect or about Vanguard. Prices: only the ballpark "most of our builds land around $1,000, one-time; the demo is free". Anyone who says stop / not interested / remove me goes on the Do-Not-Contact list and gets no further outreach.
A8: A4 | B8: Facebook groups & Messenger sweep | C8: Daily, 10:00am | D8: Claude in Chrome on your computer (logged into Facebook) | E8: Paste into Claude in Chrome and set to repeat daily | F8: Do my Facebook sweep for Vanguard (websites for US local businesses, about $1,000 one-time, free demo first). Do not post, comment, react, add friends or message anyone. 1. Messenger: open https://www.facebook.com/messages/ including Message Requests. For each unread thread or one where they wrote last, classify the reply: Reply types (pick one per conversation): Interested · Price question · Send info · Wants demo · Not now · Has a website · Referral · Partner · Not interested · Opt-out · Auto-reply · Wrong person · Booked · Who are you and draft my response (under 80 words, uses the Reply Playbook in my spreadsheet: ballpark price only, offer the free demo, book with [Calendly link]). 2. Groups: open each group in my list [GROUP LINKS]. In each, search for posts from the last 48 hours containing: website, web designer, web developer, recommend, anyone know, need a site. Read the group rules once and note whether service offers are allowed. 3. For each post where someone needs a website or asks for a recommendation: group, author, link, what they need, a drafted public comment (helpful, says who I am, offers a free demo) and a drafted follow-up DM. Only draft a DM where they asked publicly or invited DMs. 4. List up to 10 other posts by local business owners where a genuinely helpful comment would fit (questions about getting more customers, Google reviews, booking, marketing), with a drafted comment that gives value and does not pitch. Output three tables: Messenger replies, Website requests, Value comments. Rules: never send, post, comment, connect, accept or decline anything without my approval in this chat. Never invent facts about a prospect or about Vanguard. Prices: only the ballpark "most of our builds land around $1,000, one-time; the demo is free". Anyone who says stop / not interested / remove me goes on the Do-Not-Contact list and gets no further outreach.
A9: A5 | B9: Cold email replies sweep | C9: Daily, 8:30am and 4:30pm | D9: Claude in Chrome on your computer (GoHighLevel Conversations, or your cold-email tool's unified inbox) | E9: Paste into Claude in Chrome once your sending tool is live | F9: Open my cold-email inbox ([GHL Conversations URL or cold-email tool unibox URL]) in a new tab. Look at every reply received since the last sweep. 1. Classify each reply: Reply types (pick one per conversation): Interested · Price question · Send info · Wants demo · Not now · Has a website · Referral · Partner · Not interested · Opt-out · Auto-reply · Wrong person · Booked · Who are you 2. Draft my reply for each (under 80 words) using the Reply Playbook: ballpark price only, demo link + Calendly link for interested replies, polite one-liner for no. 3. Opt-outs ("stop", "remove me", "unsubscribe", angry replies): do not draft a reply; list them so I can add them to the suppression list today. 4. Auto-replies: note the return date as the next follow-up date. 5. Output a table: sender, business, reply type, one-line summary, drafted reply, next stage, follow-up date. Also report today's numbers if the tool shows them: sent, opens if tracked, replies, bounces. Rules: never send, post, comment, connect, accept or decline anything without my approval in this chat. Never invent facts about a prospect or about Vanguard. Prices: only the ballpark "most of our builds land around $1,000, one-time; the demo is free". Anyone who says stop / not interested / remove me goes on the Do-Not-Contact list and gets no further outreach.
A10: A6 | B10: Weekly review | C10: Fridays, 4:00pm | D10: Any Claude chat — attach this workbook | E10: Run manually each Friday | F10: Attached is my Vanguard outreach workbook. Review this week: 1. From 'Daily Log', total each activity for this week and compare with 'Daily KPIs' targets. Which channels and days fell short? 2. From 'Lead Tracker', count leads by stage and by channel, list every OVERDUE follow-up, and list conversations that went quiet for 5+ days. 3. Compare actual conversion rates (conversations per touch, calls per conversation) with the planning assumptions in 'Funnel Math'. Say which assumptions to change and to what. 4. Give me the 3 changes for next week that would most likely add booked calls, ranked, and anything I should stop doing. Keep it under 300 words plus the tables.
A11: A7 | B11: Cold email sending | C11: Weekdays, continuous | D11: Your sending tool (GHL workflow or Instantly/Smartlead) | E11: Set up after warm-up | F11: Not a Claude prompt. Load the EM-01 → EM-04 sequence, 20–25 sends per inbox per day, stop on reply, suppression list on.
A12: A8 | B12: Follow-up reminders | C12: Daily | D12: Lead Tracker 'Overdue?' column, or GHL tasks | E12: Ready | F12: Filter Lead Tracker by Overdue? = OVERDUE each morning, or create a GHL task for each next action date.

Sheet Rules & Limits
A1: Rules & Limits
A2: Keep the accounts and the business safe. Limits change; when a platform warns you, slow down.
A4: Channel | B4: Rule | C4: Why
A5: LinkedIn | B5: No bots or tools that auto-send, auto-connect or scrape. Claude drafts; you send. | C5: LinkedIn's User Agreement bans automated activity; accounts get restricted.
A6: LinkedIn | B6: Stay at or under about 75 connection requests a week; withdraw invites pending 3+ weeks. | C6: LinkedIn caps weekly invitations (commonly around 100) and watches acceptance rates.
A7: Facebook | B7: Read each group's rules before posting. Never mass-DM group members; only DM people who asked or engaged. | C7: Groups remove members for spam; Facebook limits accounts that send many messages to strangers.
A8: Facebook | B8: Don't paste the same comment or DM word-for-word many times a day. | C8: Repeated identical text is a spam signal.
A9: Email | B9: Include your real name, Vanguard, a physical mailing address and a working opt-out in every email; honour opt-outs fast; no misleading subjects. | C9: US CAN-SPAM Act.
A10: Email | B10: Use a separate sending domain with SPF, DKIM and DMARC; warm up 2–3 weeks; 20–25 sends per inbox per day; verify addresses; keep bounces under 3%. | C10: Protects your main domain's deliverability.
A11: Reddit | B11: Follow each subreddit's rules, disclose that you run Vanguard, lead with useful advice, and keep self-promotion a small part of your activity. | C11: Reddit and moderators ban accounts for spam.
A12: Calls / SMS | B12: Same rules as the setters: DNC scrub, 8am–9pm their time, texts only with verbal consent. | C12: TCPA and state telemarketing rules.
A13: All | B13: Never invent facts about a prospect or about Vanguard. Only the price ballpark; never exact quotes, discounts or payment plans in DMs. | C13: Honesty is the brand; and it matches the setter script.
A14: All | B14: Keep one Do-Not-Contact list across all channels. Add people the same day they ask. | C14: Respect and compliance.
A15: Outlook connector | B15: The Mailbox connector's free plan allows 5 calls a day; job A1 is written to use 4. | C15: If you add more email jobs, upgrade the connector.

Sheet Lists
A1: Stages | B1: Reply types | C1: Channels
A2: New | B2: Interested | C2: LinkedIn
A3: Contacted | B3: Price question | C3: Facebook
A4: Connected | B4: Send info | C4: Email
A5: Conversation | B5: Wants demo | C5: Reddit
A6: Demo building | B6: Not now | C6: Referral
A7: Demo sent | B7: Has a website | C7: Event
A8: Call booked | B8: Referral | C8: Other
A9: Showed | B9: Partner
A10: Won | B10: Not interested
A11: Nurture | B11: Opt-out
A12: Lost | B12: Auto-reply
A13: Do not contact | B13: Wrong person
B14: Booked
B15: Who are you
